pytubepp/__init__.py
pytubepp/config.py
pytubepp/download.py
pytubepp/main.py
pytubepp/postinstaller.py
pytubepp/postprocess.py
pytubepp/utils.py
pytubepp-1.1.9.dist-info/LICENSE
pytubepp-1.1.9.dist-info/METADATA
pytubepp-1.1.9.dist-info/WHEEL
pytubepp-1.1.9.dist-info/entry_points.txt
pytubepp-1.1.9.dist-info/top_level.txt
pytubepp-1.1.9.dist-info/RECORD
