Metadata-Version: 2.2
Name: pytubepp
Version: 1.1.9
Summary: A Simple CLI Tool to Download Your Favorite YouTube Videos Effortlessly!
Author-email: Subhamoy Biswas <hey@neosubhamoy.com>
License: MIT
Project-URL: Homepage, https://github.com/neosubhamoy/pytubepp
Project-URL: Bug Reports, https://github.com/neosubhamoy/pytubepp/issues
Keywords: youtube,download,video,pytube,cli
Classifier: Development Status :: 5 - Production/Stable
Classifier: Environment :: Console
Classifier: Intended Audience :: Developers
Classifier: License :: OSI Approved :: MIT License
Classifier: Natural Language :: English
Classifier: Operating System :: OS Independent
Classifier: Programming Language :: Python :: 3.8
Classifier: Programming Language :: Python :: 3.9
Classifier: Programming Language :: Python :: 3.10
Classifier: Programming Language :: Python :: 3.11
Classifier: Programming Language :: Python :: 3.12
Classifier: Programming Language :: Python :: 3.13
Classifier: Programming Language :: Python
Classifier: Topic :: Internet
Classifier: Topic :: Multimedia :: Video
Classifier: Topic :: Multimedia :: Sound/Audio :: Conversion
Classifier: Topic :: Multimedia :: Video :: Conversion
Classifier: Topic :: Software Development :: Libraries :: Python Modules
Classifier: Topic :: Terminals
Classifier: Topic :: Utilities
Requires-Python: >=3.8
License-File: LICENSE
Requires-Dist: pytubefix
Requires-Dist: requests
Requires-Dist: ffmpy
Requires-Dist: mutagen
Requires-Dist: tabulate
Requires-Dist: tqdm
Requires-Dist: appdirs
Requires-Dist: rich
Requires-Dist: setuptools
